compressible_flow/__init__.py
compressible_flow/compressible_flow.py
compressible_flow-0.1.10.dist-info/LICENSE
compressible_flow-0.1.10.dist-info/METADATA
compressible_flow-0.1.10.dist-info/WHEEL
compressible_flow-0.1.10.dist-info/RECORD
