Metadata-Version: 2.1
Name: compressible-flow
Version: 0.1.10
Summary: Functions for working with compressible inviscid flow of gases
License: MIT
Author: itorre
Author-email: iacopo.torre@upc.edu
Requires-Python: >=3.8,<4.0
Classifier: License :: OSI Approved :: MIT License
Classifier: Programming Language :: Python :: 3
Classifier: Programming Language :: Python :: 3.8
Classifier: Programming Language :: Python :: 3.9
Classifier: Programming Language :: Python :: 3.10
Classifier: Programming Language :: Python :: 3.11
Classifier: Programming Language :: Python :: 3.12
Requires-Dist: numpy (>=1,<2)
Requires-Dist: scipy (>=1,<2)
